{
  "main": {
    "id": "f8ee75a97f52b70d",
    "type": "split",
    "children": [
      {
        "id": "78a1ed31c7216a05",
        "type": "tabs",
        "children": [
          {
            "id": "baeddae18b25164d",
            "type": "leaf",
            "state": {
              "type": "markdown",
              "state": {
                "file": "theory/web app/notes.md",
                "mode": "source",
                "source": false
              }
            }
          },
          {
            "id": "98ff08366fa594a3",
            "type": "leaf",
            "state": {
              "type": "markdown",
              "state": {
                "file": "theory/linux/initial.md",
                "mode": "source",
                "source": false
              }
            }
          }
        ],
        "currentTab": 1
      }
    ],
    "direction": "vertical"
  },
  "left": {
    "id": "b5136cba8d110f00",
    "type": "split",
    "children": [
      {
        "id": "8b969d7ea331f0c1",
        "type": "tabs",
        "children": [
          {
            "id": "2a5674e8a40b3010",
            "type": "leaf",
            "state": {
              "type": "file-explorer",
              "state": {
                "sortOrder": "alphabetical"
              }
            }
          },
          {
            "id": "60684a51f3496415",
            "type": "leaf",
            "state": {
              "type": "search",
              "state": {
                "query": "",
                "matchingCase": false,
                "explainSearch": false,
                "collapseAll": false,
                "extraContext": false,
                "sortOrder": "alphabetical"
              }
            }
          },
          {
            "id": "50ce1dae21fefafe",
            "type": "leaf",
            "state": {
              "type": "markdown",
              "state": {
                "file": "theory/web app/notes.md",
                "mode": "source",
                "source": false
              }
            }
          }
        ]
      }
    ],
    "direction": "horizontal",
    "width": 262.5
  },
  "right": {
    "id": "da0d4f6e2ba8bc0f",
    "type": "split",
    "children": [
      {
        "id": "7cfab64be3e89e23",
        "type": "tabs",
        "children": [
          {
            "id": "02fc227be61399f9",
            "type": "leaf",
            "state": {
              "type": "backlink",
              "state": {
                "file": "theory/linux/initial.md",
                "collapseAll": false,
                "extraContext": false,
                "sortOrder": "alphabetical",
                "showSearch": false,
                "searchQuery": "",
                "backlinkCollapsed": false,
                "unlinkedCollapsed": true
              }
            }
          }
        ]
      }
    ],
    "direction": "horizontal",
    "width": 300,
    "collapsed": true
  },
  "active": "98ff08366fa594a3",
  "lastOpenFiles": [
    "tools/web/burp.md",
    "theory/web app/OWASP top 10/A01 2021 Broken Access Control.md",
    "theory/web app/notes.md",
    "theory/web app/enumeration.md",
    "not sorted yet.md",
    "note to self.md",
    "The big plans after tomorrow.md",
    "supplementary.md",
    "tools/basic b17(h/tar.md",
    "theory/web app/OWASP top 10.md"
  ]
}